{"Width":25,"Depth":25,"GridTiles":[{"widthPosition":0,"depthPosition":0,"moisture":94,"Vegetation":3,"Height":0.8538016676902771},{"widthPosition":0,"depthPosition":1,"moisture":100,"Vegetation":3,"Height":0.009999999776482582},{"widthPosition":0,"depthPosition":2,"moisture":58,"Vegetation":2,"Height":0.8111211657524109},{"widthPosition":0,"depthPosition":3,"moisture":62,"Vegetation":2,"Height":0.8173484802246094},{"widthPosition":0,"depthPosition":4,"moisture":64,"Vegetation":2,"Height":0.8494685888290405},{"widthPosition":0,"depthPosition":5,"moisture":63,"Vegetation":2,"Height":0.8317747116088867},{"widthPosition":0,"depthPosition":6,"moisture":61,"Vegetation":2,"Height":0.7372880578041077},{"widthPosition":0,"depthPosition":7,"moisture":58,"Vegetation":2,"Height":0.708830714225769},{"widthPosition":0,"depthPosition":8,"moisture":56,"Vegetation":2,"Height":0.6657102704048157},{"widthPosition":0,"depthPosition":9,"moisture":55,"Vegetation":2,"Height":0.6434269547462463},{"widthPosition":0,"depthPosition":10,"moisture":55,"Vegetation":2,"Height":0.6907442212104797},{"widthPosition":0,"depthPosition":11,"moisture":53,"Vegetation":2,"Height":0.771338701248169},{"widthPosition":0,"depthPosition":12,"moisture":49,"Vegetation":0,"Height":0.8781116008758545},{"widthPosition":0,"depthPosition":13,"moisture":44,"Vegetation":0,"Height":0.9613993763923645},{"widthPosition":0,"depthPosition":14,"moisture":40,"Vegetation":0,"Height":0.9335786700248718},{"widthPosition":0,"depthPosition":15,"moisture":37,"Vegetation":0,"Height":0.9032471179962158},{"widthPosition":0,"depthPosition":16,"moisture":36,"Vegetation":0,"Height":0.8497374057769775},{"widthPosition":0,"depthPosition":17,"moisture":37,"Vegetation":0,"Height":0.7738503813743591},{"widthPosition":0,"depthPosition":18,"moisture":41,"Vegetation":0,"Height":0.7297194600105286},{"widthPosition":0,"depthPosition":19,"moisture":45,"Vegetation":0,"Height":0.7068809270858765},{"widthPosition":0,"depthPosition":20,"moisture":50,"Vegetation":2,"Height":0.7171284556388855},{"widthPosition":0,"depthPosition":21,"moisture":57,"Vegetation":2,"Height":0.6954874992370606},{"widthPosition":0,"depthPosition":22,"moisture":64,"Vegetation":2,"Height":0.6990037560462952},{"widthPosition":0,"depthPosition":23,"moisture":71,"Vegetation":3,"Height":0.7558800578117371},{"widthPosition":0,"depthPosition":24,"moisture":75,"Vegetation":3,"Height":0.8169012665748596},{"widthPosition":1,"depthPosition":0,"moisture":89,"Vegetation":3,"Height":0.5588576197624207},{"widthPosition":1,"depthPosition":1,"moisture":100,"Vegetation":3,"Height":0.009999999776482582},{"widthPosition":1,"depthPosition":2,"moisture":53,"Vegetation":2,"Height":0.600417971611023},{"widthPosition":1,"depthPosition":3,"moisture":57,"Vegetation":2,"Height":0.6131919622421265},{"widthPosition":1,"depthPosition":4,"moisture":60,"Vegetation":2,"Height":0.6268625855445862},{"widthPosition":1,"depthPosition":5,"moisture":59,"Vegetation":2,"Height":0.6194174885749817},{"widthPosition":1,"depthPosition":6,"moisture":57,"Vegetation":2,"Height":0.6429734230041504},{"widthPosition":1,"depthPosition":7,"moisture":54,"Vegetation":0,"Height":0.6594148874282837},{"widthPosition":1,"depthPosition":8,"moisture":53,"Vegetation":2,"Height":0.6649211049079895},{"widthPosition":1,"depthPosition":9,"moisture":52,"Vegetation":0,"Height":0.6671092510223389},{"widthPosition":1,"depthPosition":10,"moisture":52,"Vegetation":2,"Height":0.709452748298645},{"widthPosition":1,"depthPosition":11,"moisture":51,"Vegetation":2,"Height":0.7782612442970276},{"widthPosition":1,"depthPosition":12,"moisture":48,"Vegetation":0,"Height":0.8529704213142395},{"widthPosition":1,"depthPosition":13,"moisture":46,"Vegetation":0,"Height":0.8972800970077515},{"widthPosition":1,"depthPosition":14,"moisture":43,"Vegetation":0,"Height":0.896671712398529},{"widthPosition":1,"depthPosition":15,"moisture":41,"Vegetation":0,"Height":0.8642638921737671},{"widthPosition":1,"depthPosition":16,"moisture":40,"Vegetation":0,"Height":0.8036494255065918},{"widthPosition":1,"depthPosition":17,"moisture":41,"Vegetation":0,"Height":0.7297191619873047},{"widthPosition":1,"depthPosition":18,"moisture":43,"Vegetation":0,"Height":0.6690556406974793},{"widthPosition":1,"depthPosition":19,"moisture":46,"Vegetation":0,"Height":0.642656683921814},{"widthPosition":1,"depthPosition":20,"moisture":49,"Vegetation":0,"Height":0.637950599193573},{"widthPosition":1,"depthPosition":21,"moisture":53,"Vegetation":2,"Height":0.6547164916992188},{"widthPosition":1,"depthPosition":22,"moisture":59,"Vegetation":2,"Height":0.7060127258300781},{"widthPosition":1,"depthPosition":23,"moisture":65,"Vegetation":2,"Height":0.7797486782073975},{"widthPosition":1,"depthPosition":24,"moisture":70,"Vegetation":3,"Height":0.8750433921813965},{"widthPosition":2,"depthPosition":0,"moisture":85,"Vegetation":3,"Height":0.3837150037288666},{"widthPosition":2,"depthPosition":1,"moisture":100,"Vegetation":3,"Height":0.009999999776482582},{"widthPosition":2,"depthPosition":2,"moisture":48,"Vegetation":0,"Height":0.39423254132270815},{"widthPosition":2,"depthPosition":3,"moisture":53,"Vegetation":2,"Height":0.3924590051174164},{"widthPosition":2,"depthPosition":4,"moisture":55,"Vegetation":2,"Height":0.3963479995727539},{"widthPosition":2,"depthPosition":5,"moisture":54,"Vegetation":2,"Height":0.3972697854042053},{"widthPosition":2,"depthPosition":6,"moisture":52,"Vegetation":2,"Height":0.444083034992218},{"widthPosition":2,"depthPosition":7,"moisture":49,"Vegetation":0,"Height":0.5039259195327759},{"widthPosition":2,"depthPosition":8,"moisture":47,"Vegetation":0,"Height":0.5450924038887024},{"widthPosition":2,"depthPosition":9,"moisture":47,"Vegetation":0,"Height":0.5991390943527222},{"widthPosition":2,"depthPosition":10,"moisture":47,"Vegetation":0,"Height":0.6744043827056885},{"widthPosition":2,"depthPosition":11,"moisture":46,"Vegetation":0,"Height":0.7593352198600769},{"widthPosition":2,"depthPosition":12,"moisture":46,"Vegetation":0,"Height":0.8204483389854431},{"widthPosition":2,"depthPosition":13,"moisture":46,"Vegetation":0,"Height":0.8595220446586609},{"widthPosition":2,"depthPosition":14,"moisture":46,"Vegetation":0,"Height":0.8591567277908325},{"widthPosition":2,"depthPosition":15,"moisture":46,"Vegetation":0,"Height":0.824616014957428},{"widthPosition":2,"depthPosition":16,"moisture":46,"Vegetation":0,"Height":0.7631148099899292},{"widthPosition":2,"depthPosition":17,"moisture":46,"Vegetation":0,"Height":0.6851922869682312},{"widthPosition":2,"depthPosition":18,"moisture":46,"Vegetation":0,"Height":0.6201615929603577},{"widthPosition":2,"depthPosition":19,"moisture":46,"Vegetation":0,"Height":0.5927377939224243},{"widthPosition":2,"depthPosition":20,"moisture":46,"Vegetation":0,"Height":0.5991230010986328},{"widthPosition":2,"depthPosition":21,"moisture":48,"Vegetation":0,"Height":0.6319311261177063},{"widthPosition":2,"depthPosition":22,"moisture":52,"Vegetation":2,"Height":0.7007642984390259},{"widthPosition":2,"depthPosition":23,"moisture":58,"Vegetation":2,"Height":0.7889143228530884},{"widthPosition":2,"depthPosition":24,"moisture":63,"Vegetation":2,"Height":0.8874404430389404},{"widthPosition":3,"depthPosition":0,"moisture":83,"Vegetation":3,"Height":0.289600670337677},{"widthPosition":3,"depthPosition":1,"moisture":100,"Vegetation":3,"Height":0.009999999776482582},{"widthPosition":3,"depthPosition":2,"moisture":96,"Vegetation":3,"Height":0.25290560722351076},{"widthPosition":3,"depthPosition":3,"moisture":100,"Vegetation":0,"Height":0.009999999776482582},{"widthPosition":3,"depthPosition":4,"moisture":51,"Vegetation":2,"Height":0.2210492491722107},{"widthPosition":3,"depthPosition":5,"moisture":50,"Vegetation":2,"Height":0.2234729677438736},{"widthPosition":3,"depthPosition":6,"moisture":47,"Vegetation":0,"Height":0.2618573307991028},{"widthPosition":3,"depthPosition":7,"moisture":44,"Vegetation":0,"Height":0.3232014775276184},{"widthPosition":3,"depthPosition":8,"moisture":42,"Vegetation":0,"Height":0.3925572633743286},{"widthPosition":3,"depthPosition":9,"moisture":41,"Vegetation":0,"Height":0.4940014183521271},{"widthPosition":3,"depthPosition":10,"moisture":41,"Vegetation":0,"Height":0.6042401790618897},{"widthPosition":3,"depthPosition":11,"moisture":42,"Vegetation":0,"Height":0.7032408714294434},{"widthPosition":3,"depthPosition":12,"moisture":44,"Vegetation":0,"Height":0.769620954990387},{"widthPosition":3,"depthPosition":13,"moisture":46,"Vegetation":0,"Height":0.8092731833457947},{"widthPosition":3,"depthPosition":14,"moisture":49,"Vegetation":0,"Height":0.8089467287063599},{"widthPosition":3,"depthPosition":15,"moisture":50,"Vegetation":2,"Height":0.7694360017776489},{"widthPosition":3,"depthPosition":16,"moisture":51,"Vegetation":2,"Height":0.709781289100647},{"widthPosition":3,"depthPosition":17,"moisture":50,"Vegetation":2,"Height":0.6400861740112305},{"widthPosition":3,"depthPosition":18,"moisture":49,"Vegetation":0,"Height":0.5839431285858154},{"widthPosition":3,"depthPosition":19,"moisture":46,"Vegetation":0,"Height":0.5603388547897339},{"widthPosition":3,"depthPosition":20,"moisture":44,"Vegetation":0,"Height":0.5691229701042175},{"widthPosition":3,"depthPosition":21,"moisture":44,"Vegetation":0,"Height":0.6102185249328613},{"widthPosition":3,"depthPosition":22,"moisture":45,"Vegetation":0,"Height":0.6869041323661804},{"widthPosition":3,"depthPosition":23,"moisture":49,"Vegetation":0,"Height":0.7800422310829163},{"widthPosition":3,"depthPosition":24,"moisture":54,"Vegetation":0,"Height":0.8752555251121521},{"widthPosition":4,"depthPosition":0,"moisture":84,"Vegetation":0,"Height":0.2846756875514984},{"widthPosition":4,"depthPosition":1,"moisture":100,"Vegetation":3,"Height":0.009999999776482582},{"widthPosition":4,"depthPosition":2,"moisture":100,"Vegetation":3,"Height":0.009999999776482582},{"widthPosition":4,"depthPosition":3,"moisture":100,"Vegetation":3,"Height":0.009999999776482582},{"widthPosition":4,"depthPosition":4,"moisture":50,"Vegetation":0,"Height":0.13741785287857057},{"widthPosition":4,"depthPosition":5,"moisture":48,"Vegetation":0,"Height":0.13709010183811189},{"widthPosition":4,"depthPosition":6,"moisture":44,"Vegetation":0,"Height":0.16845087707042695},{"widthPosition":4,"depthPosition":7,"moisture":40,"Vegetation":0,"Height":0.22066399455070496},{"widthPosition":4,"depthPosition":8,"moisture":38,"Vegetation":0,"Height":0.283596932888031},{"widthPosition":4,"depthPosition":9,"moisture":37,"Vegetation":0,"Height":0.4068908989429474},{"widthPosition":4,"depthPosition":10,"moisture":37,"Vegetation":0,"Height":0.5440002679824829},{"widthPosition":4,"depthPosition":11,"moisture":39,"Vegetation":0,"Height":0.6551299691200256},{"widthPosition":4,"depthPosition":12,"moisture":43,"Vegetation":0,"Height":0.7187309861183167},{"widthPosition":4,"depthPosition":13,"moisture":47,"Vegetation":0,"Height":0.7586358785629273},{"widthPosition":4,"depthPosition":14,"moisture":52,"Vegetation":2,"Height":0.7590794563293457},{"widthPosition":4,"depthPosition":15,"moisture":55,"Vegetation":2,"Height":0.7177368402481079},{"widthPosition":4,"depthPosition":16,"moisture":56,"Vegetation":2,"Height":0.6582667827606201},{"widthPosition":4,"depthPosition":17,"moisture":54,"Vegetation":2,"Height":0.593007504940033},{"widthPosition":4,"depthPosition":18,"moisture":51,"Vegetation":2,"Height":0.5496034026145935},{"widthPosition":4,"depthPosition":19,"moisture":47,"Vegetation":0,"Height":0.532463014125824},{"widthPosition":4,"depthPosition":20,"moisture":43,"Vegetation":0,"Height":0.5446560978889465},{"widthPosition":4,"depthPosition":21,"moisture":40,"Vegetation":0,"Height":0.5902879238128662},{"widthPosition":4,"depthPosition":22,"moisture":39,"Vegetation":0,"Height":0.6764798760414124},{"widthPosition":4,"depthPosition":23,"moisture":41,"Vegetation":0,"Height":0.7706688642501831},{"widthPosition":4,"depthPosition":24,"moisture":46,"Vegetation":0,"Height":0.8566878437995911},{"widthPosition":5,"depthPosition":0,"moisture":38,"Vegetation":0,"Height":0.24580030143260957},{"widthPosition":5,"depthPosition":1,"moisture":45,"Vegetation":0,"Height":0.20690682530403138},{"widthPosition":5,"depthPosition":2,"moisture":100,"Vegetation":3,"Height":0.009999999776482582},{"widthPosition":5,"depthPosition":3,"moisture":100,"Vegetation":3,"Height":0.009999999776482582},{"widthPosition":5,"depthPosition":4,"moisture":100,"Vegetation":3,"Height":0.009999999776482582},{"widthPosition":5,"depthPosition":5,"moisture":99,"Vegetation":3,"Height":0.09018883109092713},{"widthPosition":5,"depthPosition":6,"moisture":94,"Vegetation":3,"Height":0.11540191620588303},{"widthPosition":5,"depthPosition":7,"moisture":40,"Vegetation":0,"Height":0.15880022943019868},{"widthPosition":5,"depthPosition":8,"moisture":37,"Vegetation":0,"Height":0.21407824754714967},{"widthPosition":5,"depthPosition":9,"moisture":36,"Vegetation":0,"Height":0.35492414236068728},{"widthPosition":5,"depthPosition":10,"moisture":37,"Vegetation":0,"Height":0.5082986354827881},{"widthPosition":5,"depthPosition":11,"moisture":39,"Vegetation":0,"Height":0.6178708672523499},{"widthPosition":5,"depthPosition":12,"moisture":44,"Vegetation":0,"Height":0.670261025428772},{"widthPosition":5,"depthPosition":13,"moisture":50,"Vegetation":2,"Height":0.7005698084831238},{"widthPosition":5,"depthPosition":14,"moisture":55,"Vegetation":2,"Height":0.6978022456169128},{"widthPosition":5,"depthPosition":15,"moisture":59,"Vegetation":2,"Height":0.6585084795951843},{"widthPosition":5,"depthPosition":16,"moisture":59,"Vegetation":2,"Height":0.6022256016731262},{"widthPosition":5,"depthPosition":17,"moisture":57,"Vegetation":2,"Height":0.5436722636222839},{"widthPosition":5,"depthPosition":18,"moisture":53,"Vegetation":2,"Height":0.5101677179336548},{"widthPosition":5,"depthPosition":19,"moisture":47,"Vegetation":0,"Height":0.5050926804542542},{"widthPosition":5,"depthPosition":20,"moisture":41,"Vegetation":0,"Height":0.5274277925491333},{"widthPosition":5,"depthPosition":21,"moisture":37,"Vegetation":0,"Height":0.5800051689147949},{"widthPosition":5,"depthPosition":22,"moisture":34,"Vegetation":0,"Height":0.6585798859596252},{"widthPosition":5,"depthPosition":23,"moisture":35,"Vegetation":0,"Height":0.7373749017715454},{"widthPosition":5,"depthPosition":24,"moisture":38,"Vegetation":0,"Height":0.8317325711250305},{"widthPosition":6,"depthPosition":0,"moisture":44,"Vegetation":0,"Height":0.19716140627861024},{"widthPosition":6,"depthPosition":1,"moisture":51,"Vegetation":2,"Height":0.17482569813728333},{"widthPosition":6,"depthPosition":2,"moisture":100,"Vegetation":3,"Height":0.009999999776482582},{"widthPosition":6,"depthPosition":3,"moisture":100,"Vegetation":3,"Height":0.009999999776482582},{"widthPosition":6,"depthPosition":4,"moisture":100,"Vegetation":3,"Height":0.009999999776482582},{"widthPosition":6,"depthPosition":5,"moisture":100,"Vegetation":3,"Height":0.009999999776482582},{"widthPosition":6,"depthPosition":6,"moisture":100,"Vegetation":0,"Height":0.009999999776482582},{"widthPosition":6,"depthPosition":7,"moisture":43,"Vegetation":0,"Height":0.10387738794088364},{"widthPosition":6,"depthPosition":8,"moisture":40,"Vegetation":0,"Height":0.14859630167484284},{"widthPosition":6,"depthPosition":9,"moisture":39,"Vegetation":0,"Height":0.2742786109447479},{"widthPosition":6,"depthPosition":10,"moisture":40,"Vegetation":0,"Height":0.42351964116096499},{"widthPosition":6,"depthPosition":11,"moisture":42,"Vegetation":0,"Height":0.5349693298339844},{"widthPosition":6,"depthPosition":12,"moisture":47,"Vegetation":0,"Height":0.600192666053772},{"widthPosition":6,"depthPosition":13,"moisture":53,"Vegetation":0,"Height":0.6329212784767151},{"widthPosition":6,"depthPosition":14,"moisture":58,"Vegetation":2,"Height":0.622385561466217},{"widthPosition":6,"depthPosition":15,"moisture":62,"Vegetation":0,"Height":0.5880011320114136},{"widthPosition":6,"depthPosition":16,"moisture":62,"Vegetation":0,"Height":0.5353739857673645},{"widthPosition":6,"depthPosition":17,"moisture":59,"Vegetation":2,"Height":0.48370593786239626},{"widthPosition":6,"depthPosition":18,"moisture":54,"Vegetation":2,"Height":0.45642656087875368},{"widthPosition":6,"depthPosition":19,"moisture":47,"Vegetation":0,"Height":0.4673766791820526},{"widthPosition":6,"depthPosition":20,"moisture":41,"Vegetation":0,"Height":0.49769580364227297},{"widthPosition":6,"depthPosition":21,"moisture":35,"Vegetation":0,"Height":0.54796302318573},{"widthPosition":6,"depthPosition":22,"moisture":31,"Vegetation":0,"Height":0.6090353727340698},{"widthPosition":6,"depthPosition":23,"moisture":30,"Vegetation":0,"Height":0.6788665056228638},{"widthPosition":6,"depthPosition":24,"moisture":33,"Vegetation":0,"Height":0.7346957325935364},{"widthPosition":7,"depthPosition":0,"moisture":51,"Vegetation":2,"Height":0.16403540968894959},{"widthPosition":7,"depthPosition":1,"moisture":57,"Vegetation":2,"Height":0.15951694548130036},{"widthPosition":7,"depthPosition":2,"moisture":62,"Vegetation":2,"Height":0.11715614795684815},{"widthPosition":7,"depthPosition":3,"moisture":64,"Vegetation":2,"Height":0.07292018085718155},{"widthPosition":7,"depthPosition":4,"moisture":63,"Vegetation":2,"Height":0.044056884944438937},{"widthPosition":7,"depthPosition":5,"moisture":100,"Vegetation":3,"Height":0.009999999776482582},{"widthPosition":7,"depthPosition":6,"moisture":100,"Vegetation":3,"Height":0.009999999776482582},{"widthPosition":7,"depthPosition":7,"moisture":49,"Vegetation":0,"Height":0.05860668048262596},{"widthPosition":7,"depthPosition":8,"moisture":46,"Vegetation":0,"Height":0.0899997130036354},{"widthPosition":7,"depthPosition":9,"moisture":45,"Vegetation":0,"Height":0.17598044872283936},{"widthPosition":7,"depthPosition":10,"moisture":46,"Vegetation":0,"Height":0.2918126881122589},{"widthPosition":7,"depthPosition":11,"moisture":48,"Vegetation":0,"Height":0.4103950560092926},{"widthPosition":7,"depthPosition":12,"moisture":52,"Vegetation":2,"Height":0.5010828971862793},{"widthPosition":7,"depthPosition":13,"moisture":58,"Vegetation":2,"Height":0.5489850044250488},{"widthPosition":7,"depthPosition":14,"moisture":62,"Vegetation":2,"Height":0.5522200465202332},{"widthPosition":7,"depthPosition":15,"moisture":64,"Vegetation":2,"Height":0.5102514624595642},{"widthPosition":7,"depthPosition":16,"moisture":63,"Vegetation":2,"Height":0.4502395987510681},{"widthPosition":7,"depthPosition":17,"moisture":60,"Vegetation":0,"Height":0.3890308737754822},{"widthPosition":7,"depthPosition":18,"moisture":54,"Vegetation":2,"Height":0.3571830987930298},{"widthPosition":7,"depthPosition":19,"moisture":47,"Vegetation":0,"Height":0.3646409511566162},{"widthPosition":7,"depthPosition":20,"moisture":40,"Vegetation":0,"Height":0.3897347152233124},{"widthPosition":7,"depthPosition":21,"moisture":34,"Vegetation":0,"Height":0.42126885056495669},{"widthPosition":7,"depthPosition":22,"moisture":30,"Vegetation":0,"Height":0.47355639934539797},{"widthPosition":7,"depthPosition":23,"moisture":28,"Vegetation":1,"Height":0.5558602809906006},{"widthPosition":7,"depthPosition":24,"moisture":29,"Vegetation":1,"Height":0.6998138427734375},{"widthPosition":8,"depthPosition":0,"moisture":57,"Vegetation":2,"Height":0.18665538728237153},{"widthPosition":8,"depthPosition":1,"moisture":63,"Vegetation":2,"Height":0.1613469421863556},{"widthPosition":8,"depthPosition":2,"moisture":68,"Vegetation":2,"Height":0.11641842126846314},{"widthPosition":8,"depthPosition":3,"moisture":70,"Vegetation":3,"Height":0.06945913285017014},{"widthPosition":8,"depthPosition":4,"moisture":69,"Vegetation":2,"Height":0.03805331885814667},{"widthPosition":8,"depthPosition":5,"moisture":100,"Vegetation":3,"Height":0.009999999776482582},{"widthPosition":8,"depthPosition":6,"moisture":100,"Vegetation":0,"Height":0.009999999776482582},{"widthPosition":8,"depthPosition":7,"moisture":55,"Vegetation":2,"Height":0.03284311667084694},{"widthPosition":8,"depthPosition":8,"moisture":53,"Vegetation":2,"Height":0.05207139998674393},{"widthPosition":8,"depthPosition":9,"moisture":52,"Vegetation":2,"Height":0.10394708067178726},{"widthPosition":8,"depthPosition":10,"moisture":52,"Vegetation":2,"Height":0.17708471417427064},{"widthPosition":8,"depthPosition":11,"moisture":54,"Vegetation":2,"Height":0.26627153158187868},{"widthPosition":8,"depthPosition":12,"moisture":58,"Vegetation":2,"Height":0.3683815598487854},{"widthPosition":8,"depthPosition":13,"moisture":62,"Vegetation":0,"Height":0.4437677264213562},{"widthPosition":8,"depthPosition":14,"moisture":65,"Vegetation":0,"Height":0.46207985281944277},{"widthPosition":8,"depthPosition":15,"moisture":66,"Vegetation":2,"Height":0.42449021339416506},{"widthPosition":8,"depthPosition":16,"moisture":64,"Vegetation":2,"Height":0.34533336758613589},{"widthPosition":8,"depthPosition":17,"moisture":60,"Vegetation":2,"Height":0.2736276090145111},{"widthPosition":8,"depthPosition":18,"moisture":54,"Vegetation":2,"Height":0.2342502623796463},{"widthPosition":8,"depthPosition":19,"moisture":47,"Vegetation":0,"Height":0.22877773642539979},{"widthPosition":8,"depthPosition":20,"moisture":40,"Vegetation":0,"Height":0.23822543025016786},{"widthPosition":8,"depthPosition":21,"moisture":34,"Vegetation":0,"Height":0.25704795122146609},{"widthPosition":8,"depthPosition":22,"moisture":28,"Vegetation":1,"Height":0.30710238218307497},{"widthPosition":8,"depthPosition":23,"moisture":26,"Vegetation":1,"Height":0.4141407012939453},{"widthPosition":8,"depthPosition":24,"moisture":26,"Vegetation":0,"Height":0.5674768090248108},{"widthPosition":9,"depthPosition":0,"moisture":60,"Vegetation":2,"Height":0.19976802170276643},{"widthPosition":9,"depthPosition":1,"moisture":66,"Vegetation":2,"Height":0.19293613731861115},{"widthPosition":9,"depthPosition":2,"moisture":70,"Vegetation":3,"Height":0.14599119126796723},{"widthPosition":9,"depthPosition":3,"moisture":72,"Vegetation":3,"Height":0.09334537386894226},{"widthPosition":9,"depthPosition":4,"moisture":71,"Vegetation":3,"Height":0.04897317290306091},{"widthPosition":9,"depthPosition":5,"moisture":100,"Vegetation":3,"Height":0.009999999776482582},{"widthPosition":9,"depthPosition":6,"moisture":100,"Vegetation":3,"Height":0.009999999776482582},{"widthPosition":9,"depthPosition":7,"moisture":100,"Vegetation":3,"Height":0.009999999776482582},{"widthPosition":9,"depthPosition":8,"moisture":100,"Vegetation":3,"Height":0.009999999776482582},{"widthPosition":9,"depthPosition":9,"moisture":55,"Vegetation":2,"Height":0.06089179590344429},{"widthPosition":9,"depthPosition":10,"moisture":56,"Vegetation":2,"Height":0.10424884408712387},{"widthPosition":9,"depthPosition":11,"moisture":57,"Vegetation":0,"Height":0.1634199619293213},{"widthPosition":9,"depthPosition":12,"moisture":61,"Vegetation":2,"Height":0.24710363149642945},{"widthPosition":9,"depthPosition":13,"moisture":64,"Vegetation":2,"Height":0.34747201204299929},{"widthPosition":9,"depthPosition":14,"moisture":66,"Vegetation":2,"Height":0.3818512260913849},{"widthPosition":9,"depthPosition":15,"moisture":66,"Vegetation":2,"Height":0.3399331569671631},{"widthPosition":9,"depthPosition":16,"moisture":63,"Vegetation":2,"Height":0.2509863078594208},{"widthPosition":9,"depthPosition":17,"moisture":58,"Vegetation":2,"Height":0.1755855530500412},{"widthPosition":9,"depthPosition":18,"moisture":51,"Vegetation":2,"Height":0.13491103053092957},{"widthPosition":9,"depthPosition":19,"moisture":44,"Vegetation":0,"Height":0.12210091203451157},{"widthPosition":9,"depthPosition":20,"moisture":38,"Vegetation":0,"Height":0.12372201681137085},{"widthPosition":9,"depthPosition":21,"moisture":31,"Vegetation":0,"Height":0.13931804895401},{"widthPosition":9,"depthPosition":22,"moisture":26,"Vegetation":1,"Height":0.184597447514534},{"widthPosition":9,"depthPosition":23,"moisture":23,"Vegetation":1,"Height":0.28445807099342348},{"widthPosition":9,"depthPosition":24,"moisture":23,"Vegetation":1,"Height":0.41106683015823367},{"widthPosition":10,"depthPosition":0,"moisture":59,"Vegetation":2,"Height":0.24689234793186189},{"widthPosition":10,"depthPosition":1,"moisture":64,"Vegetation":0,"Height":0.21019810438156129},{"widthPosition":10,"depthPosition":2,"moisture":67,"Vegetation":0,"Height":0.1595172882080078},{"widthPosition":10,"depthPosition":3,"moisture":68,"Vegetation":2,"Height":0.0988922044634819},{"widthPosition":10,"depthPosition":4,"moisture":68,"Vegetation":2,"Height":0.05760805681347847},{"widthPosition":10,"depthPosition":5,"moisture":100,"Vegetation":3,"Height":0.009999999776482582},{"widthPosition":10,"depthPosition":6,"moisture":100,"Vegetation":3,"Height":0.009999999776482582},{"widthPosition":10,"depthPosition":7,"moisture":100,"Vegetation":3,"Height":0.009999999776482582},{"widthPosition":10,"depthPosition":8,"moisture":100,"Vegetation":3,"Height":0.009999999776482582},{"widthPosition":10,"depthPosition":9,"moisture":100,"Vegetation":3,"Height":0.009999999776482582},{"widthPosition":10,"depthPosition":10,"moisture":56,"Vegetation":2,"Height":0.06585761904716492},{"widthPosition":10,"depthPosition":11,"moisture":57,"Vegetation":0,"Height":0.10801579058170319},{"widthPosition":10,"depthPosition":12,"moisture":60,"Vegetation":2,"Height":0.17357352375984193},{"widthPosition":10,"depthPosition":13,"moisture":63,"Vegetation":2,"Height":0.27633997797966006},{"widthPosition":10,"depthPosition":14,"moisture":64,"Vegetation":2,"Height":0.31382638216018679},{"widthPosition":10,"depthPosition":15,"moisture":63,"Vegetation":2,"Height":0.26371994614601138},{"widthPosition":10,"depthPosition":16,"moisture":59,"Vegetation":0,"Height":0.17261835932731629},{"widthPosition":10,"depthPosition":17,"moisture":54,"Vegetation":2,"Height":0.10806906223297119},{"widthPosition":10,"depthPosition":18,"moisture":47,"Vegetation":0,"Height":0.0729212760925293},{"widthPosition":10,"depthPosition":19,"moisture":90,"Vegetation":3,"Height":0.058784257620573047},{"widthPosition":10,"depthPosition":20,"moisture":83,"Vegetation":3,"Height":0.058098092675209048},{"widthPosition":10,"depthPosition":21,"moisture":77,"Vegetation":3,"Height":0.07102420926094055},{"widthPosition":10,"depthPosition":22,"moisture":22,"Vegetation":1,"Height":0.11104007065296173},{"widthPosition":10,"depthPosition":23,"moisture":20,"Vegetation":1,"Height":0.19695231318473817},{"widthPosition":10,"depthPosition":24,"moisture":20,"Vegetation":1,"Height":0.2862987518310547},{"widthPosition":11,"depthPosition":0,"moisture":54,"Vegetation":0,"Height":0.22626043856143952},{"widthPosition":11,"depthPosition":1,"moisture":57,"Vegetation":2,"Height":0.2032039612531662},{"widthPosition":11,"depthPosition":2,"moisture":58,"Vegetation":2,"Height":0.1573023647069931},{"widthPosition":11,"depthPosition":3,"moisture":59,"Vegetation":2,"Height":0.10816436260938645},{"widthPosition":11,"depthPosition":4,"moisture":59,"Vegetation":2,"Height":0.06708266586065293},{"widthPosition":11,"depthPosition":5,"moisture":57,"Vegetation":2,"Height":0.04296642914414406},{"widthPosition":11,"depthPosition":6,"moisture":55,"Vegetation":2,"Height":0.026235055178403856},{"widthPosition":11,"depthPosition":7,"moisture":100,"Vegetation":3,"Height":0.009999999776482582},{"widthPosition":11,"depthPosition":8,"moisture":100,"Vegetation":3,"Height":0.009999999776482582},{"widthPosition":11,"depthPosition":9,"moisture":100,"Vegetation":3,"Height":0.009999999776482582},{"widthPosition":11,"depthPosition":10,"moisture":100,"Vegetation":3,"Height":0.009999999776482582},{"widthPosition":11,"depthPosition":11,"moisture":54,"Vegetation":2,"Height":0.07751421630382538},{"widthPosition":11,"depthPosition":12,"moisture":56,"Vegetation":2,"Height":0.1307516247034073},{"widthPosition":11,"depthPosition":13,"moisture":59,"Vegetation":2,"Height":0.2307167947292328},{"widthPosition":11,"depthPosition":14,"moisture":60,"Vegetation":2,"Height":0.2667511999607086},{"widthPosition":11,"depthPosition":15,"moisture":58,"Vegetation":0,"Height":0.21602895855903626},{"widthPosition":11,"depthPosition":16,"moisture":54,"Vegetation":2,"Height":0.12968766689300538},{"widthPosition":11,"depthPosition":17,"moisture":49,"Vegetation":0,"Height":0.07071449607610703},{"widthPosition":11,"depthPosition":18,"moisture":100,"Vegetation":0,"Height":0.009999999776482582},{"widthPosition":11,"depthPosition":19,"moisture":100,"Vegetation":3,"Height":0.009999999776482582},{"widthPosition":11,"depthPosition":20,"moisture":100,"Vegetation":0,"Height":0.009999999776482582},{"widthPosition":11,"depthPosition":21,"moisture":100,"Vegetation":3,"Height":0.009999999776482582},{"widthPosition":11,"depthPosition":22,"moisture":18,"Vegetation":1,"Height":0.0740208625793457},{"widthPosition":11,"depthPosition":23,"moisture":17,"Vegetation":1,"Height":0.1459454894065857},{"widthPosition":11,"depthPosition":24,"moisture":19,"Vegetation":1,"Height":0.24032479524612428},{"widthPosition":12,"depthPosition":0,"moisture":47,"Vegetation":0,"Height":0.21200832724571229},{"widthPosition":12,"depthPosition":1,"moisture":47,"Vegetation":0,"Height":0.21329359710216523},{"widthPosition":12,"depthPosition":2,"moisture":47,"Vegetation":0,"Height":0.1817283034324646},{"widthPosition":12,"depthPosition":3,"moisture":47,"Vegetation":0,"Height":0.13772784173488618},{"widthPosition":12,"depthPosition":4,"moisture":47,"Vegetation":0,"Height":0.09411570429801941},{"widthPosition":12,"depthPosition":5,"moisture":47,"Vegetation":0,"Height":0.06299889087677002},{"widthPosition":12,"depthPosition":6,"moisture":47,"Vegetation":0,"Height":0.0383429080247879},{"widthPosition":12,"depthPosition":7,"moisture":47,"Vegetation":0,"Height":0.02431945875287056},{"widthPosition":12,"depthPosition":8,"moisture":97,"Vegetation":3,"Height":0.018566157668828965},{"widthPosition":12,"depthPosition":9,"moisture":100,"Vegetation":3,"Height":0.009999999776482582},{"widthPosition":12,"depthPosition":10,"moisture":100,"Vegetation":3,"Height":0.009999999776482582},{"widthPosition":12,"depthPosition":11,"moisture":48,"Vegetation":0,"Height":0.05705281347036362},{"widthPosition":12,"depthPosition":12,"moisture":51,"Vegetation":2,"Height":0.09986814111471176},{"widthPosition":12,"depthPosition":13,"moisture":54,"Vegetation":2,"Height":0.19148527085781098},{"widthPosition":12,"depthPosition":14,"moisture":55,"Vegetation":2,"Height":0.2318604290485382},{"widthPosition":12,"depthPosition":15,"moisture":54,"Vegetation":2,"Height":0.18617801368236543},{"widthPosition":12,"depthPosition":16,"moisture":50,"Vegetation":2,"Height":0.1088331863284111},{"widthPosition":12,"depthPosition":17,"moisture":94,"Vegetation":0,"Height":0.05328323319554329},{"widthPosition":12,"depthPosition":18,"moisture":100,"Vegetation":3,"Height":0.009999999776482582},{"widthPosition":12,"depthPosition":19,"moisture":100,"Vegetation":3,"Height":0.009999999776482582},{"widthPosition":12,"depthPosition":20,"moisture":100,"Vegetation":3,"Height":0.009999999776482582},{"widthPosition":12,"depthPosition":21,"moisture":100,"Vegetation":3,"Height":0.009999999776482582},{"widthPosition":12,"depthPosition":22,"moisture":15,"Vegetation":0,"Height":0.05791574716567993},{"widthPosition":12,"depthPosition":23,"moisture":16,"Vegetation":1,"Height":0.12455198168754578},{"widthPosition":12,"depthPosition":24,"moisture":20,"Vegetation":1,"Height":0.19546329975128175},{"widthPosition":13,"depthPosition":0,"moisture":39,"Vegetation":0,"Height":0.22390040755271913},{"widthPosition":13,"depthPosition":1,"moisture":37,"Vegetation":0,"Height":0.24865640699863435},{"widthPosition":13,"depthPosition":2,"moisture":35,"Vegetation":0,"Height":0.2362864911556244},{"widthPosition":13,"depthPosition":3,"moisture":35,"Vegetation":0,"Height":0.2092638462781906},{"widthPosition":13,"depthPosition":4,"moisture":35,"Vegetation":0,"Height":0.17971280217170716},{"widthPosition":13,"depthPosition":5,"moisture":36,"Vegetation":0,"Height":0.14427325129508973},{"widthPosition":13,"depthPosition":6,"moisture":38,"Vegetation":0,"Height":0.09568939357995987},{"widthPosition":13,"depthPosition":7,"moisture":40,"Vegetation":0,"Height":0.05308711901307106},{"widthPosition":13,"depthPosition":8,"moisture":41,"Vegetation":0,"Height":0.028005149215459825},{"widthPosition":13,"depthPosition":9,"moisture":91,"Vegetation":0,"Height":0.022927358746528627},{"widthPosition":13,"depthPosition":10,"moisture":100,"Vegetation":3,"Height":0.009999999776482582},{"widthPosition":13,"depthPosition":11,"moisture":43,"Vegetation":0,"Height":0.04020122438669205},{"widthPosition":13,"depthPosition":12,"moisture":46,"Vegetation":0,"Height":0.06894278526306153},{"widthPosition":13,"depthPosition":13,"moisture":49,"Vegetation":0,"Height":0.13274945318698884},{"widthPosition":13,"depthPosition":14,"moisture":51,"Vegetation":2,"Height":0.17035478353500367},{"widthPosition":13,"depthPosition":15,"moisture":51,"Vegetation":0,"Height":0.13956999778747559},{"widthPosition":13,"depthPosition":16,"moisture":48,"Vegetation":0,"Height":0.08546268939971924},{"widthPosition":13,"depthPosition":17,"moisture":92,"Vegetation":3,"Height":0.04355480521917343},{"widthPosition":13,"depthPosition":18,"moisture":100,"Vegetation":3,"Height":0.009999999776482582},{"widthPosition":13,"depthPosition":19,"moisture":100,"Vegetation":0,"Height":0.009999999776482582},{"widthPosition":13,"depthPosition":20,"moisture":100,"Vegetation":3,"Height":0.009999999776482582},{"widthPosition":13,"depthPosition":21,"moisture":100,"Vegetation":0,"Height":0.009999999776482582},{"widthPosition":13,"depthPosition":22,"moisture":15,"Vegetation":1,"Height":0.05585101619362831},{"widthPosition":13,"depthPosition":23,"moisture":16,"Vegetation":1,"Height":0.11906815320253372},{"widthPosition":13,"depthPosition":24,"moisture":21,"Vegetation":1,"Height":0.2073846161365509},{"widthPosition":14,"depthPosition":0,"moisture":33,"Vegetation":0,"Height":0.28724971413612368},{"widthPosition":14,"depthPosition":1,"moisture":29,"Vegetation":1,"Height":0.30750882625579836},{"widthPosition":14,"depthPosition":2,"moisture":26,"Vegetation":1,"Height":0.3074410855770111},{"widthPosition":14,"depthPosition":3,"moisture":25,"Vegetation":0,"Height":0.30668944120407107},{"widthPosition":14,"depthPosition":4,"moisture":26,"Vegetation":1,"Height":0.30585187673568728},{"widthPosition":14,"depthPosition":5,"moisture":28,"Vegetation":1,"Height":0.280961811542511},{"widthPosition":14,"depthPosition":6,"moisture":31,"Vegetation":0,"Height":0.20402564108371736},{"widthPosition":14,"depthPosition":7,"moisture":35,"Vegetation":0,"Height":0.11704972386360169},{"widthPosition":14,"depthPosition":8,"moisture":36,"Vegetation":0,"Height":0.055128064006567},{"widthPosition":14,"depthPosition":9,"moisture":87,"Vegetation":3,"Height":0.03500406816601753},{"widthPosition":14,"depthPosition":10,"moisture":100,"Vegetation":3,"Height":0.009999999776482582},{"widthPosition":14,"depthPosition":11,"moisture":39,"Vegetation":0,"Height":0.03226323425769806},{"widthPosition":14,"depthPosition":12,"moisture":43,"Vegetation":0,"Height":0.0473758690059185},{"widthPosition":14,"depthPosition":13,"moisture":47,"Vegetation":0,"Height":0.08466022461652756},{"widthPosition":14,"depthPosition":14,"moisture":49,"Vegetation":0,"Height":0.11200246959924698},{"widthPosition":14,"depthPosition":15,"moisture":50,"Vegetation":2,"Height":0.10399952530860901},{"widthPosition":14,"depthPosition":16,"moisture":48,"Vegetation":0,"Height":0.07364378869533539},{"widthPosition":14,"depthPosition":17,"moisture":93,"Vegetation":3,"Height":0.04502510279417038},{"widthPosition":14,"depthPosition":18,"moisture":100,"Vegetation":3,"Height":0.009999999776482582},{"widthPosition":14,"depthPosition":19,"moisture":100,"Vegetation":3,"Height":0.009999999776482582},{"widthPosition":14,"depthPosition":20,"moisture":23,"Vegetation":1,"Height":0.02100348100066185},{"widthPosition":14,"depthPosition":21,"moisture":18,"Vegetation":1,"Height":0.03195806220173836},{"widthPosition":14,"depthPosition":22,"moisture":16,"Vegetation":1,"Height":0.06450677663087845},{"widthPosition":14,"depthPosition":23,"moisture":18,"Vegetation":1,"Height":0.1294124871492386},{"widthPosition":14,"depthPosition":24,"moisture":24,"Vegetation":1,"Height":0.21112462878227235},{"widthPosition":15,"depthPosition":0,"moisture":31,"Vegetation":0,"Height":0.3821932077407837},{"widthPosition":15,"depthPosition":1,"moisture":26,"Vegetation":1,"Height":0.3660745918750763},{"widthPosition":15,"depthPosition":2,"moisture":22,"Vegetation":1,"Height":0.3667263090610504},{"widthPosition":15,"depthPosition":3,"moisture":20,"Vegetation":1,"Height":0.37895554304122927},{"widthPosition":15,"depthPosition":4,"moisture":21,"Vegetation":1,"Height":0.4108918309211731},{"widthPosition":15,"depthPosition":5,"moisture":24,"Vegetation":1,"Height":0.43129631876945498},{"widthPosition":15,"depthPosition":6,"moisture":29,"Vegetation":0,"Height":0.3398529887199402},{"widthPosition":15,"depthPosition":7,"moisture":33,"Vegetation":0,"Height":0.21430402994155885},{"widthPosition":15,"depthPosition":8,"moisture":36,"Vegetation":0,"Height":0.11114410310983658},{"widthPosition":15,"depthPosition":9,"moisture":86,"Vegetation":3,"Height":0.06538515537977219},{"widthPosition":15,"depthPosition":10,"moisture":100,"Vegetation":3,"Height":0.009999999776482582},{"widthPosition":15,"depthPosition":11,"moisture":89,"Vegetation":3,"Height":0.03564757481217384},{"widthPosition":15,"depthPosition":12,"moisture":43,"Vegetation":0,"Height":0.04042229428887367},{"widthPosition":15,"depthPosition":13,"moisture":47,"Vegetation":0,"Height":0.06399808079004288},{"widthPosition":15,"depthPosition":14,"moisture":51,"Vegetation":2,"Height":0.08535145223140717},{"widthPosition":15,"depthPosition":15,"moisture":52,"Vegetation":2,"Height":0.0852106437087059},{"widthPosition":15,"depthPosition":16,"moisture":51,"Vegetation":2,"Height":0.07663531601428986},{"widthPosition":15,"depthPosition":17,"moisture":47,"Vegetation":0,"Height":0.0618780218064785},{"widthPosition":15,"depthPosition":18,"moisture":41,"Vegetation":0,"Height":0.050152186304330829},{"widthPosition":15,"depthPosition":19,"moisture":34,"Vegetation":0,"Height":0.04091113060712814},{"widthPosition":15,"depthPosition":20,"moisture":27,"Vegetation":1,"Height":0.03954575955867767},{"widthPosition":15,"depthPosition":21,"moisture":22,"Vegetation":1,"Height":0.048534248024225238},{"widthPosition":15,"depthPosition":22,"moisture":20,"Vegetation":1,"Height":0.07868292927742005},{"widthPosition":15,"depthPosition":23,"moisture":21,"Vegetation":1,"Height":0.13825879991054536},{"widthPosition":15,"depthPosition":24,"moisture":26,"Vegetation":0,"Height":0.22714224457740785},{"widthPosition":16,"depthPosition":0,"moisture":34,"Vegetation":0,"Height":0.42015790939331057},{"widthPosition":16,"depthPosition":1,"moisture":28,"Vegetation":1,"Height":0.4173218607902527},{"widthPosition":16,"depthPosition":2,"moisture":23,"Vegetation":1,"Height":0.4160845875740051},{"widthPosition":16,"depthPosition":3,"moisture":21,"Vegetation":0,"Height":0.4410456717014313},{"widthPosition":16,"depthPosition":4,"moisture":22,"Vegetation":1,"Height":0.49495458602905276},{"widthPosition":16,"depthPosition":5,"moisture":26,"Vegetation":1,"Height":0.5475184917449951},{"widthPosition":16,"depthPosition":6,"moisture":31,"Vegetation":0,"Height":0.4648614823818207},{"widthPosition":16,"depthPosition":7,"moisture":36,"Vegetation":0,"Height":0.30786800384521487},{"widthPosition":16,"depthPosition":8,"moisture":39,"Vegetation":0,"Height":0.1803053766489029},{"widthPosition":16,"depthPosition":9,"moisture":89,"Vegetation":3,"Height":0.10435741394758225},{"widthPosition":16,"depthPosition":10,"moisture":100,"Vegetation":3,"Height":0.009999999776482582},{"widthPosition":16,"depthPosition":11,"moisture":100,"Vegetation":0,"Height":0.009999999776482582},{"widthPosition":16,"depthPosition":12,"moisture":96,"Vegetation":3,"Height":0.03648042306303978},{"widthPosition":16,"depthPosition":13,"moisture":100,"Vegetation":3,"Height":0.009999999776482582},{"widthPosition":16,"depthPosition":14,"moisture":55,"Vegetation":2,"Height":0.06520756334066391},{"widthPosition":16,"depthPosition":15,"moisture":57,"Vegetation":2,"Height":0.07091254740953446},{"widthPosition":16,"depthPosition":16,"moisture":56,"Vegetation":2,"Height":0.08368536084890366},{"widthPosition":16,"depthPosition":17,"moisture":52,"Vegetation":2,"Height":0.0937035009264946},{"widthPosition":16,"depthPosition":18,"moisture":47,"Vegetation":0,"Height":0.0951111912727356},{"widthPosition":16,"depthPosition":19,"moisture":40,"Vegetation":0,"Height":0.08875967562198639},{"widthPosition":16,"depthPosition":20,"moisture":33,"Vegetation":0,"Height":0.07804044336080551},{"widthPosition":16,"depthPosition":21,"moisture":28,"Vegetation":1,"Height":0.07780960947275162},{"widthPosition":16,"depthPosition":22,"moisture":24,"Vegetation":1,"Height":0.09693405777215958},{"widthPosition":16,"depthPosition":23,"moisture":24,"Vegetation":1,"Height":0.14251545071601869},{"widthPosition":16,"depthPosition":24,"moisture":28,"Vegetation":1,"Height":0.20900434255599976},{"widthPosition":17,"depthPosition":0,"moisture":40,"Vegetation":0,"Height":0.4804530143737793},{"widthPosition":17,"depthPosition":1,"moisture":34,"Vegetation":0,"Height":0.4676066040992737},{"widthPosition":17,"depthPosition":2,"moisture":29,"Vegetation":1,"Height":0.4734591245651245},{"widthPosition":17,"depthPosition":3,"moisture":27,"Vegetation":1,"Height":0.5046755075454712},{"widthPosition":17,"depthPosition":4,"moisture":28,"Vegetation":0,"Height":0.5685139894485474},{"widthPosition":17,"depthPosition":5,"moisture":32,"Vegetation":0,"Height":0.6268383264541626},{"widthPosition":17,"depthPosition":6,"moisture":37,"Vegetation":0,"Height":0.5626485347747803},{"widthPosition":17,"depthPosition":7,"moisture":42,"Vegetation":0,"Height":0.40585654973983767},{"widthPosition":17,"depthPosition":8,"moisture":45,"Vegetation":0,"Height":0.26187700033187868},{"widthPosition":17,"depthPosition":9,"moisture":45,"Vegetation":0,"Height":0.1538029909133911},{"widthPosition":17,"depthPosition":10,"moisture":96,"Vegetation":3,"Height":0.08361327648162842},{"widthPosition":17,"depthPosition":11,"moisture":100,"Vegetation":3,"Height":0.009999999776482582},{"widthPosition":17,"depthPosition":12,"moisture":100,"Vegetation":0,"Height":0.009999999776482582},{"widthPosition":17,"depthPosition":13,"moisture":100,"Vegetation":3,"Height":0.009999999776482582},{"widthPosition":17,"depthPosition":14,"moisture":62,"Vegetation":2,"Height":0.04752736911177635},{"widthPosition":17,"depthPosition":15,"moisture":64,"Vegetation":2,"Height":0.057752881199121478},{"widthPosition":17,"depthPosition":16,"moisture":63,"Vegetation":2,"Height":0.08429518342018128},{"widthPosition":17,"depthPosition":17,"moisture":59,"Vegetation":2,"Height":0.12304560840129852},{"widthPosition":17,"depthPosition":18,"moisture":53,"Vegetation":2,"Height":0.15600359439849854},{"widthPosition":17,"depthPosition":19,"moisture":47,"Vegetation":0,"Height":0.1642264723777771},{"widthPosition":17,"depthPosition":20,"moisture":40,"Vegetation":0,"Height":0.15348058938980103},{"widthPosition":17,"depthPosition":21,"moisture":34,"Vegetation":0,"Height":0.13593539595603944},{"widthPosition":17,"depthPosition":22,"moisture":29,"Vegetation":1,"Height":0.1313183307647705},{"widthPosition":17,"depthPosition":23,"moisture":27,"Vegetation":1,"Height":0.14509892463684083},{"widthPosition":17,"depthPosition":24,"moisture":29,"Vegetation":0,"Height":0.17240314185619355},{"widthPosition":18,"depthPosition":0,"moisture":47,"Vegetation":0,"Height":0.5237065553665161},{"widthPosition":18,"depthPosition":1,"moisture":41,"Vegetation":0,"Height":0.5151649117469788},{"widthPosition":18,"depthPosition":2,"moisture":36,"Vegetation":0,"Height":0.5241056084632874},{"widthPosition":18,"depthPosition":3,"moisture":34,"Vegetation":0,"Height":0.5572839379310608},{"widthPosition":18,"depthPosition":4,"moisture":35,"Vegetation":0,"Height":0.6228030920028687},{"widthPosition":18,"depthPosition":5,"moisture":39,"Vegetation":0,"Height":0.6921887397766113},{"widthPosition":18,"depthPosition":6,"moisture":43,"Vegetation":0,"Height":0.663419246673584},{"widthPosition":18,"depthPosition":7,"moisture":48,"Vegetation":0,"Height":0.5219537019729614},{"widthPosition":18,"depthPosition":8,"moisture":51,"Vegetation":2,"Height":0.3680278956890106},{"widthPosition":18,"depthPosition":9,"moisture":52,"Vegetation":2,"Height":0.22092567384243012},{"widthPosition":18,"depthPosition":10,"moisture":52,"Vegetation":2,"Height":0.11846045404672623},{"widthPosition":18,"depthPosition":11,"moisture":54,"Vegetation":0,"Height":0.056683409959077838},{"widthPosition":18,"depthPosition":12,"moisture":100,"Vegetation":3,"Height":0.009999999776482582},{"widthPosition":18,"depthPosition":13,"moisture":100,"Vegetation":0,"Height":0.009999999776482582},{"widthPosition":18,"depthPosition":14,"moisture":68,"Vegetation":0,"Height":0.03984371945261955},{"widthPosition":18,"depthPosition":15,"moisture":70,"Vegetation":3,"Height":0.05223214998841286},{"widthPosition":18,"depthPosition":16,"moisture":69,"Vegetation":2,"Height":0.08784423023462296},{"widthPosition":18,"depthPosition":17,"moisture":65,"Vegetation":0,"Height":0.15138451755046845},{"widthPosition":18,"depthPosition":18,"moisture":59,"Vegetation":2,"Height":0.22576139867305757},{"widthPosition":18,"depthPosition":19,"moisture":53,"Vegetation":2,"Height":0.25680792331695559},{"widthPosition":18,"depthPosition":20,"moisture":46,"Vegetation":0,"Height":0.23962198197841645},{"widthPosition":18,"depthPosition":21,"moisture":40,"Vegetation":0,"Height":0.20329317450523377},{"widthPosition":18,"depthPosition":22,"moisture":34,"Vegetation":0,"Height":0.16907021403312684},{"widthPosition":18,"depthPosition":23,"moisture":30,"Vegetation":0,"Height":0.14812511205673219},{"widthPosition":18,"depthPosition":24,"moisture":29,"Vegetation":1,"Height":0.12848731875419618},{"widthPosition":19,"depthPosition":0,"moisture":53,"Vegetation":2,"Height":0.5525054931640625},{"widthPosition":19,"depthPosition":1,"moisture":48,"Vegetation":0,"Height":0.5602520704269409},{"widthPosition":19,"depthPosition":2,"moisture":44,"Vegetation":0,"Height":0.5747267603874207},{"widthPosition":19,"depthPosition":3,"moisture":42,"Vegetation":0,"Height":0.6069223880767822},{"widthPosition":19,"depthPosition":4,"moisture":42,"Vegetation":0,"Height":0.6668938398361206},{"widthPosition":19,"depthPosition":5,"moisture":45,"Vegetation":0,"Height":0.7382259368896484},{"widthPosition":19,"depthPosition":6,"moisture":49,"Vegetation":0,"Height":0.75897616147995},{"widthPosition":19,"depthPosition":7,"moisture":53,"Vegetation":2,"Height":0.6726685762405396},{"widthPosition":19,"depthPosition":8,"moisture":55,"Vegetation":2,"Height":0.5349274277687073},{"widthPosition":19,"depthPosition":9,"moisture":56,"Vegetation":0,"Height":0.34973669052124026},{"widthPosition":19,"depthPosition":10,"moisture":55,"Vegetation":2,"Height":0.19141432642936707},{"widthPosition":19,"depthPosition":11,"moisture":57,"Vegetation":2,"Height":0.08977963030338288},{"widthPosition":19,"depthPosition":12,"moisture":100,"Vegetation":3,"Height":0.009999999776482582},{"widthPosition":19,"depthPosition":13,"moisture":100,"Vegetation":3,"Height":0.009999999776482582},{"widthPosition":19,"depthPosition":14,"moisture":100,"Vegetation":3,"Height":0.009999999776482582},{"widthPosition":19,"depthPosition":15,"moisture":72,"Vegetation":0,"Height":0.05557943508028984},{"widthPosition":19,"depthPosition":16,"moisture":72,"Vegetation":3,"Height":0.09983162581920624},{"widthPosition":19,"depthPosition":17,"moisture":68,"Vegetation":2,"Height":0.18410061299800874},{"widthPosition":19,"depthPosition":18,"moisture":63,"Vegetation":2,"Height":0.27943357825279238},{"widthPosition":19,"depthPosition":19,"moisture":57,"Vegetation":2,"Height":0.3198729157447815},{"widthPosition":19,"depthPosition":20,"moisture":50,"Vegetation":2,"Height":0.29923009872436526},{"widthPosition":19,"depthPosition":21,"moisture":43,"Vegetation":0,"Height":0.2520447373390198},{"widthPosition":19,"depthPosition":22,"moisture":37,"Vegetation":0,"Height":0.20122739672660829},{"widthPosition":19,"depthPosition":23,"moisture":32,"Vegetation":0,"Height":0.16195416450500489},{"widthPosition":19,"depthPosition":24,"moisture":28,"Vegetation":1,"Height":0.11541732400655747},{"widthPosition":20,"depthPosition":0,"moisture":59,"Vegetation":2,"Height":0.5863124132156372},{"widthPosition":20,"depthPosition":1,"moisture":55,"Vegetation":2,"Height":0.5857224464416504},{"widthPosition":20,"depthPosition":2,"moisture":51,"Vegetation":2,"Height":0.6062813997268677},{"widthPosition":20,"depthPosition":3,"moisture":50,"Vegetation":0,"Height":0.647283673286438},{"widthPosition":20,"depthPosition":4,"moisture":50,"Vegetation":2,"Height":0.7035858035087586},{"widthPosition":20,"depthPosition":5,"moisture":51,"Vegetation":2,"Height":0.7731234431266785},{"widthPosition":20,"depthPosition":6,"moisture":53,"Vegetation":2,"Height":0.8311644792556763},{"widthPosition":20,"depthPosition":7,"moisture":55,"Vegetation":2,"Height":0.8209037184715271},{"widthPosition":20,"depthPosition":8,"moisture":56,"Vegetation":2,"Height":0.7365344762802124},{"widthPosition":20,"depthPosition":9,"moisture":56,"Vegetation":2,"Height":0.5458145141601563},{"widthPosition":20,"depthPosition":10,"moisture":55,"Vegetation":0,"Height":0.33638647198677065},{"widthPosition":20,"depthPosition":11,"moisture":56,"Vegetation":2,"Height":0.17557929456233979},{"widthPosition":20,"depthPosition":12,"moisture":100,"Vegetation":3,"Height":0.009999999776482582},{"widthPosition":20,"depthPosition":13,"moisture":100,"Vegetation":3,"Height":0.009999999776482582},{"widthPosition":20,"depthPosition":14,"moisture":100,"Vegetation":3,"Height":0.009999999776482582},{"widthPosition":20,"depthPosition":15,"moisture":100,"Vegetation":3,"Height":0.009999999776482582},{"widthPosition":20,"depthPosition":16,"moisture":69,"Vegetation":2,"Height":0.12393057346343994},{"widthPosition":20,"depthPosition":17,"moisture":66,"Vegetation":2,"Height":0.21380679309368134},{"widthPosition":20,"depthPosition":18,"moisture":62,"Vegetation":2,"Height":0.31332632899284365},{"widthPosition":20,"depthPosition":19,"moisture":56,"Vegetation":0,"Height":0.35511910915374758},{"widthPosition":20,"depthPosition":20,"moisture":51,"Vegetation":2,"Height":0.3367365002632141},{"widthPosition":20,"depthPosition":21,"moisture":44,"Vegetation":0,"Height":0.2867562472820282},{"widthPosition":20,"depthPosition":22,"moisture":88,"Vegetation":3,"Height":0.2336401343345642},{"widthPosition":20,"depthPosition":23,"moisture":82,"Vegetation":3,"Height":0.18466565012931825},{"widthPosition":20,"depthPosition":24,"moisture":28,"Vegetation":0,"Height":0.15413117408752442},{"widthPosition":21,"depthPosition":0,"moisture":62,"Vegetation":2,"Height":0.5761776566505432},{"widthPosition":21,"depthPosition":1,"moisture":60,"Vegetation":2,"Height":0.5783707499504089},{"widthPosition":21,"depthPosition":2,"moisture":58,"Vegetation":2,"Height":0.6094609498977661},{"widthPosition":21,"depthPosition":3,"moisture":57,"Vegetation":0,"Height":0.6670935750007629},{"widthPosition":21,"depthPosition":4,"moisture":57,"Vegetation":2,"Height":0.7372675538063049},{"widthPosition":21,"depthPosition":5,"moisture":56,"Vegetation":2,"Height":0.8093937039375305},{"widthPosition":21,"depthPosition":6,"moisture":56,"Vegetation":2,"Height":0.8721900582313538},{"widthPosition":21,"depthPosition":7,"moisture":56,"Vegetation":2,"Height":0.8975167870521545},{"widthPosition":21,"depthPosition":8,"moisture":54,"Vegetation":2,"Height":0.868743896484375},{"widthPosition":21,"depthPosition":9,"moisture":52,"Vegetation":0,"Height":0.6983718276023865},{"widthPosition":21,"depthPosition":10,"moisture":51,"Vegetation":2,"Height":0.4580628275871277},{"widthPosition":21,"depthPosition":11,"moisture":50,"Vegetation":2,"Height":0.2711544930934906},{"widthPosition":21,"depthPosition":12,"moisture":52,"Vegetation":2,"Height":0.17542579770088197},{"widthPosition":21,"depthPosition":13,"moisture":100,"Vegetation":3,"Height":0.009999999776482582},{"widthPosition":21,"depthPosition":14,"moisture":100,"Vegetation":3,"Height":0.009999999776482582},{"widthPosition":21,"depthPosition":15,"moisture":100,"Vegetation":0,"Height":0.009999999776482582},{"widthPosition":21,"depthPosition":16,"moisture":62,"Vegetation":2,"Height":0.15578581392765046},{"widthPosition":21,"depthPosition":17,"moisture":60,"Vegetation":2,"Height":0.24463099241256715},{"widthPosition":21,"depthPosition":18,"moisture":57,"Vegetation":2,"Height":0.3427167534828186},{"widthPosition":21,"depthPosition":19,"moisture":53,"Vegetation":2,"Height":0.3922417461872101},{"widthPosition":21,"depthPosition":20,"moisture":48,"Vegetation":0,"Height":0.3822599947452545},{"widthPosition":21,"depthPosition":21,"moisture":93,"Vegetation":3,"Height":0.3389742374420166},{"widthPosition":21,"depthPosition":22,"moisture":100,"Vegetation":3,"Height":0.009999999776482582},{"widthPosition":21,"depthPosition":23,"moisture":100,"Vegetation":3,"Height":0.009999999776482582},{"widthPosition":21,"depthPosition":24,"moisture":28,"Vegetation":1,"Height":0.16951392590999604},{"widthPosition":22,"depthPosition":0,"moisture":63,"Vegetation":2,"Height":0.5548732280731201},{"widthPosition":22,"depthPosition":1,"moisture":63,"Vegetation":2,"Height":0.5771409869194031},{"widthPosition":22,"depthPosition":2,"moisture":64,"Vegetation":2,"Height":0.6127273440361023},{"widthPosition":22,"depthPosition":3,"moisture":64,"Vegetation":2,"Height":0.6843239665031433},{"widthPosition":22,"depthPosition":4,"moisture":63,"Vegetation":2,"Height":0.7698055505752564},{"widthPosition":22,"depthPosition":5,"moisture":61,"Vegetation":2,"Height":0.8479760885238648},{"widthPosition":22,"depthPosition":6,"moisture":58,"Vegetation":2,"Height":0.9043014049530029},{"widthPosition":22,"depthPosition":7,"moisture":54,"Vegetation":0,"Height":0.9283087849617004},{"widthPosition":22,"depthPosition":8,"moisture":51,"Vegetation":2,"Height":0.9066068530082703},{"widthPosition":22,"depthPosition":9,"moisture":47,"Vegetation":0,"Height":0.7758454084396362},{"widthPosition":22,"depthPosition":10,"moisture":44,"Vegetation":0,"Height":0.5597179532051086},{"widthPosition":22,"depthPosition":11,"moisture":42,"Vegetation":0,"Height":0.3689180910587311},{"widthPosition":22,"depthPosition":12,"moisture":42,"Vegetation":0,"Height":0.25238174200057986},{"widthPosition":22,"depthPosition":13,"moisture":44,"Vegetation":0,"Height":0.2061825543642044},{"widthPosition":22,"depthPosition":14,"moisture":97,"Vegetation":3,"Height":0.18791036307811738},{"widthPosition":22,"depthPosition":15,"moisture":100,"Vegetation":0,"Height":0.009999999776482582},{"widthPosition":22,"depthPosition":16,"moisture":51,"Vegetation":2,"Height":0.2020045965909958},{"widthPosition":22,"depthPosition":17,"moisture":52,"Vegetation":2,"Height":0.2843409478664398},{"widthPosition":22,"depthPosition":18,"moisture":50,"Vegetation":0,"Height":0.38764312863349917},{"widthPosition":22,"depthPosition":19,"moisture":47,"Vegetation":0,"Height":0.45024916529655459},{"widthPosition":22,"depthPosition":20,"moisture":44,"Vegetation":0,"Height":0.45170775055885317},{"widthPosition":22,"depthPosition":21,"moisture":90,"Vegetation":3,"Height":0.40705516934394839},{"widthPosition":22,"depthPosition":22,"moisture":100,"Vegetation":3,"Height":0.009999999776482582},{"widthPosition":22,"depthPosition":23,"moisture":33,"Vegetation":0,"Height":0.28565728664398196},{"widthPosition":22,"depthPosition":24,"moisture":29,"Vegetation":1,"Height":0.2202858030796051},{"widthPosition":23,"depthPosition":0,"moisture":61,"Vegetation":2,"Height":0.6006344556808472},{"widthPosition":23,"depthPosition":1,"moisture":64,"Vegetation":2,"Height":0.5988644361495972},{"widthPosition":23,"depthPosition":2,"moisture":67,"Vegetation":2,"Height":0.6350473761558533},{"widthPosition":23,"depthPosition":3,"moisture":68,"Vegetation":0,"Height":0.7132132053375244},{"widthPosition":23,"depthPosition":4,"moisture":67,"Vegetation":2,"Height":0.808955192565918},{"widthPosition":23,"depthPosition":5,"moisture":64,"Vegetation":2,"Height":0.8880003094673157},{"widthPosition":23,"depthPosition":6,"moisture":59,"Vegetation":2,"Height":0.937533438205719},{"widthPosition":23,"depthPosition":7,"moisture":53,"Vegetation":0,"Height":0.9547905921936035},{"widthPosition":23,"depthPosition":8,"moisture":47,"Vegetation":0,"Height":0.9321831464767456},{"widthPosition":23,"depthPosition":9,"moisture":42,"Vegetation":0,"Height":0.8534033894538879},{"widthPosition":23,"depthPosition":10,"moisture":37,"Vegetation":0,"Height":0.6936143636703491},{"widthPosition":23,"depthPosition":11,"moisture":34,"Vegetation":0,"Height":0.5215961933135986},{"widthPosition":23,"depthPosition":12,"moisture":32,"Vegetation":0,"Height":0.4004330039024353},{"widthPosition":23,"depthPosition":13,"moisture":33,"Vegetation":0,"Height":0.3413574695587158},{"widthPosition":23,"depthPosition":14,"moisture":35,"Vegetation":0,"Height":0.3201729953289032},{"widthPosition":23,"depthPosition":15,"moisture":38,"Vegetation":0,"Height":0.3035518229007721},{"widthPosition":23,"depthPosition":16,"moisture":41,"Vegetation":0,"Height":0.30506834387779238},{"widthPosition":23,"depthPosition":17,"moisture":43,"Vegetation":0,"Height":0.36070600152015688},{"widthPosition":23,"depthPosition":18,"moisture":93,"Vegetation":3,"Height":0.45726287364959719},{"widthPosition":23,"depthPosition":19,"moisture":91,"Vegetation":3,"Height":0.5207374691963196},{"widthPosition":23,"depthPosition":20,"moisture":89,"Vegetation":3,"Height":0.5236582159996033},{"widthPosition":23,"depthPosition":21,"moisture":100,"Vegetation":3,"Height":0.009999999776482582},{"widthPosition":23,"depthPosition":22,"moisture":100,"Vegetation":3,"Height":0.009999999776482582},{"widthPosition":23,"depthPosition":23,"moisture":35,"Vegetation":0,"Height":0.35427796840667727},{"widthPosition":23,"depthPosition":24,"moisture":34,"Vegetation":0,"Height":0.2779656946659088},{"widthPosition":24,"depthPosition":0,"moisture":58,"Vegetation":2,"Height":0.6220413446426392},{"widthPosition":24,"depthPosition":1,"moisture":63,"Vegetation":0,"Height":0.6183353066444397},{"widthPosition":24,"depthPosition":2,"moisture":68,"Vegetation":2,"Height":0.6394463181495667},{"widthPosition":24,"depthPosition":3,"moisture":71,"Vegetation":3,"Height":0.715082585811615},{"widthPosition":24,"depthPosition":4,"moisture":71,"Vegetation":3,"Height":0.8664037585258484},{"widthPosition":24,"depthPosition":5,"moisture":67,"Vegetation":2,"Height":0.9550766348838806},{"widthPosition":24,"depthPosition":6,"moisture":60,"Vegetation":2,"Height":0.990403413772583},{"widthPosition":24,"depthPosition":7,"moisture":52,"Vegetation":2,"Height":1.0},{"widthPosition":24,"depthPosition":8,"moisture":44,"Vegetation":0,"Height":0.9856563210487366},{"widthPosition":24,"depthPosition":9,"moisture":38,"Vegetation":0,"Height":0.9528716206550598},{"widthPosition":24,"depthPosition":10,"moisture":32,"Vegetation":0,"Height":0.9388096928596497},{"widthPosition":24,"depthPosition":11,"moisture":28,"Vegetation":1,"Height":0.6981996297836304},{"widthPosition":24,"depthPosition":12,"moisture":25,"Vegetation":1,"Height":0.5116726160049439},{"widthPosition":24,"depthPosition":13,"moisture":24,"Vegetation":1,"Height":0.5016405582427979},{"widthPosition":24,"depthPosition":14,"moisture":26,"Vegetation":1,"Height":0.48694655299186709},{"widthPosition":24,"depthPosition":15,"moisture":29,"Vegetation":0,"Height":0.47343772649765017},{"widthPosition":24,"depthPosition":16,"moisture":33,"Vegetation":0,"Height":0.4190419316291809},{"widthPosition":24,"depthPosition":17,"moisture":86,"Vegetation":3,"Height":0.3928735554218292},{"widthPosition":24,"depthPosition":18,"moisture":100,"Vegetation":3,"Height":0.009999999776482582},{"widthPosition":24,"depthPosition":19,"moisture":100,"Vegetation":3,"Height":0.009999999776482582},{"widthPosition":24,"depthPosition":20,"moisture":100,"Vegetation":3,"Height":0.009999999776482582},{"widthPosition":24,"depthPosition":21,"moisture":100,"Vegetation":0,"Height":0.009999999776482582},{"widthPosition":24,"depthPosition":22,"moisture":100,"Vegetation":3,"Height":0.009999999776482582},{"widthPosition":24,"depthPosition":23,"moisture":39,"Vegetation":0,"Height":0.43309295177459719},{"widthPosition":24,"depthPosition":24,"moisture":40,"Vegetation":0,"Height":0.3374006152153015}]}